pqon/__init__.py
pqon/cli.py
pqon/parser.py
pqon-0.0.1.dist-info/entry_points.txt
pqon-0.0.1.dist-info/LICENSE
pqon-0.0.1.dist-info/WHEEL
pqon-0.0.1.dist-info/METADATA
pqon-0.0.1.dist-info/RECORD
