Metadata-Version: 2.1
Name: pqon
Version: 0.0.1
Summary: Manipulate JSON similarly to jq
License: MIT
Author: Malthe Jørgensen
Author-email: malthe.jorgensen@gmail.com
Requires-Python: >=3.6,<4.0
Classifier: License :: OSI Approved :: MIT License
Classifier: Programming Language :: Python :: 3
Classifier: Programming Language :: Python :: 3.10
Classifier: Programming Language :: Python :: 3.6
Classifier: Programming Language :: Python :: 3.7
Classifier: Programming Language :: Python :: 3.8
Classifier: Programming Language :: Python :: 3.9
